setup.py
ProcessInteract.egg-info/PKG-INFO
ProcessInteract.egg-info/SOURCES.txt
ProcessInteract.egg-info/dependency_links.txt
ProcessInteract.egg-info/top_level.txt
processinteract/__init__.py
processinteract/main.py